LICENSE.txt
MANIFEST.in
NOTICE
README.md
setup.cfg
setup.py
expertbridge/__init__.py
expertbridge/app.py
expertbridge/config.py
expertbridge/constants.py
expertbridge/dataframe.py
expertbridge/errors.py
expertbridge/exceptions.py
expertbridge/expertbridge_typing.py
expertbridge/forms.py
expertbridge/jinja_context.py
expertbridge/legacy.py
expertbridge/result_set.py
expertbridge/schemas.py
expertbridge/sql_lab.py
expertbridge/sql_parse.py
expertbridge/stats_logger.py
expertbridge/viz.py
expertbridge-frontend/package.json
expertbridge.egg-info/PKG-INFO
expertbridge.egg-info/SOURCES.txt
expertbridge.egg-info/dependency_links.txt
expertbridge.egg-info/entry_points.txt
expertbridge.egg-info/not-zip-safe
expertbridge.egg-info/requires.txt
expertbridge.egg-info/top_level.txt
expertbridge/advanced_data_type/__init__.py
expertbridge/advanced_data_type/api.py
expertbridge/advanced_data_type/schemas.py
expertbridge/advanced_data_type/types.py
expertbridge/advanced_data_type/plugins/__init__.py
expertbridge/advanced_data_type/plugins/internet_address.py
expertbridge/advanced_data_type/plugins/internet_port.py
expertbridge/annotation_layers/__init__.py
expertbridge/annotation_layers/api.py
expertbridge/annotation_layers/dao.py
expertbridge/annotation_layers/filters.py
expertbridge/annotation_layers/schemas.py
expertbridge/annotation_layers/annotations/__init__.py
expertbridge/annotation_layers/annotations/api.py
expertbridge/annotation_layers/annotations/dao.py
expertbridge/annotation_layers/annotations/filters.py
expertbridge/annotation_layers/annotations/schemas.py
expertbridge/annotation_layers/annotations/commands/__init__.py
expertbridge/annotation_layers/annotations/commands/bulk_delete.py
expertbridge/annotation_layers/annotations/commands/create.py
expertbridge/annotation_layers/annotations/commands/delete.py
expertbridge/annotation_layers/annotations/commands/exceptions.py
expertbridge/annotation_layers/annotations/commands/update.py
expertbridge/annotation_layers/commands/__init__.py
expertbridge/annotation_layers/commands/bulk_delete.py
expertbridge/annotation_layers/commands/create.py
expertbridge/annotation_layers/commands/delete.py
expertbridge/annotation_layers/commands/exceptions.py
